latent/__init__.py
latent/activations.py
latent/callbacks.py
latent/layers.py
latent/losses.py
latent/utils.py
latent/models/__init__.py
latent/models/ae.py
latent/models/twae.py
latent/models/vae.py
latent/modules/__init__.py
latent/modules/decoder.py
latent/modules/encoder.py
latent-0.1.dist-info/LICENSE
latent-0.1.dist-info/METADATA
latent-0.1.dist-info/WHEEL
latent-0.1.dist-info/top_level.txt
latent-0.1.dist-info/RECORD
