Metadata-Version: 2.1
Name: latent
Version: 0.1
Summary: Latent spaces for single cells
Home-page: UNKNOWN
Author: Jonas Simon Fleck
Author-email: jonas.fleck@bsse.ethz.ch
License: MIT
Platform: UNKNOWN
Requires-Python: >=3.8.5
Requires-Dist: numpy (>=1.18.5)
Requires-Dist: tensorflow (>=2.3.1)
Requires-Dist: tensorflow-probability (>=0.11.1)
